huaweicloudsdksmnglobal/__init__.py
huaweicloudsdksmnglobal/v2/__init__.py
huaweicloudsdksmnglobal/v2/smnglobal_async_client.py
huaweicloudsdksmnglobal/v2/smnglobal_client.py
huaweicloudsdksmnglobal/v2/model/__init__.py
huaweicloudsdksmnglobal/v2/model/create_subscription_user_request.py
huaweicloudsdksmnglobal/v2/model/create_subscription_user_request_body.py
huaweicloudsdksmnglobal/v2/model/create_subscription_user_request_email_endpoint_info.py
huaweicloudsdksmnglobal/v2/model/create_subscription_user_request_http_endpoint_info.py
huaweicloudsdksmnglobal/v2/model/create_subscription_user_request_https_endpoint_info.py
huaweicloudsdksmnglobal/v2/model/create_subscription_user_request_sms_endpoint_info.py
huaweicloudsdksmnglobal/v2/model/create_subscription_user_response.py
huaweicloudsdksmnglobal/v2/model/delete_subscription_user_request.py
huaweicloudsdksmnglobal/v2/model/delete_subscription_user_response.py
huaweicloudsdksmnglobal/v2/model/list_subscription_user_request.py
huaweicloudsdksmnglobal/v2/model/list_subscription_user_response.py
huaweicloudsdksmnglobal/v2/model/list_subscription_user_response_email_endpoint_info.py
huaweicloudsdksmnglobal/v2/model/list_subscription_user_response_http_endpoint_info.py
huaweicloudsdksmnglobal/v2/model/list_subscription_user_response_https_endpoint_info.py
huaweicloudsdksmnglobal/v2/model/list_subscription_user_response_item_info.py
huaweicloudsdksmnglobal/v2/model/list_subscription_user_response_sms_endpoint_info.py
huaweicloudsdksmnglobal/v2/model/update_subscription_user_request.py
huaweicloudsdksmnglobal/v2/model/update_subscription_user_request_body.py
huaweicloudsdksmnglobal/v2/model/update_subscription_user_response.py
huaweicloudsdksmnglobal/v2/region/__init__.py
huaweicloudsdksmnglobal/v2/region/smnglobal_region.py
huaweicloudsdksmnglobal-3.1.184.dist-info/METADATA
huaweicloudsdksmnglobal-3.1.184.dist-info/WHEEL
huaweicloudsdksmnglobal-3.1.184.dist-info/licenses/LICENSE
huaweicloudsdksmnglobal-3.1.184.dist-info/RECORD
